[{"fold_id": 0, "model_name": "nn", "feature_name": "cpc_finetuning_21600", "scores_valid": {"accuracy": 0.6238888888888889, "cnt_samples": 5400, "cnt_features": 512}, "scores_test": {"accuracy": 0.6073333333333333, "cnt_samples": 3000, "cnt_features": 512}}, {"fold_id": 1, "model_name": "nn", "feature_name": "cpc_finetuning_21600", "scores_valid": {"accuracy": 0.6135185185185185, "cnt_samples": 5400, "cnt_features": 512}, "scores_test": {"accuracy": 0.6186666666666667, "cnt_samples": 3000, "cnt_features": 512}}, {"fold_id": 2, "model_name": "nn", "feature_name": "cpc_finetuning_21600", "scores_valid": {"accuracy": 0.6316666666666667, "cnt_samples": 5400, "cnt_features": 512}, "scores_test": {"accuracy": 0.6086666666666667, "cnt_samples": 3000, "cnt_features": 512}}, {"fold_id": 3, "model_name": "nn", "feature_name": "cpc_finetuning_21600", "scores_valid": {"accuracy": 0.6142592592592593, "cnt_samples": 5400, "cnt_features": 512}, "scores_test": {"accuracy": 0.6103333333333333, "cnt_samples": 3000, "cnt_features": 512}}, {"fold_id": 4, "model_name": "nn", "feature_name": "cpc_finetuning_21600", "scores_valid": {"accuracy": 0.6131481481481481, "cnt_samples": 5400, "cnt_features": 512}, "scores_test": {"accuracy": 0.6286666666666667, "cnt_samples": 3000, "cnt_features": 512}}]