[
  {
    "fold_id": "0",
    "model_name": "nn",
    "feature_name": "cpc_finetuning_100000",
    "scores_valid": {
      "accuracy": 0.5169310569763184
    },
    "scores_test": {
      "accuracy": 0.5225459933280945
    }
  },
  {
    "fold_id": "1",
    "model_name": "nn",
    "feature_name": "cpc_finetuning_100000",
    "scores_valid": {
      "accuracy": 0.5179239511489868
    },
    "scores_test": {
      "accuracy": 0.5227466225624084
    }
  },
  {
    "fold_id": "2",
    "model_name": "nn",
    "feature_name": "cpc_finetuning_100000",
    "scores_valid": {
      "accuracy": 0.5191307067871094
    },
    "scores_test": {
      "accuracy": 0.5228720307350159
    }
  },
  {
    "fold_id": "3",
    "model_name": "nn",
    "feature_name": "cpc_finetuning_100000",
    "scores_valid": {
      "accuracy": 0.5197149515151978
    },
    "scores_test": {
      "accuracy": 0.5224206447601318
    }
  },
  {
    "fold_id": "4",
    "model_name": "nn",
    "feature_name": "cpc_finetuning_100000",
    "scores_valid": {
      "accuracy": 0.5217827558517456
    },
    "scores_test": {
      "accuracy": 0.5229723453521729
    }
  }
]