[{"fold_id": 0, "model_name": "nn", "feature_name": "target_scores", "scores_valid": {"auroc": 0.8597213145032961, "cnt_samples": 1512, "cnt_features": 48}, "scores_test": {"auroc": 0.867326034007876, "cnt_samples": 840, "cnt_features": 48}}, {"fold_id": 1, "model_name": "nn", "feature_name": "target_scores", "scores_valid": {"auroc": 0.8601084763582634, "cnt_samples": 1512, "cnt_features": 48}, "scores_test": {"auroc": 0.8614930231499397, "cnt_samples": 840, "cnt_features": 48}}, {"fold_id": 2, "model_name": "nn", "feature_name": "target_scores", "scores_valid": {"auroc": 0.8634188878154125, "cnt_samples": 1512, "cnt_features": 48}, "scores_test": {"auroc": 0.8708884386879425, "cnt_samples": 840, "cnt_features": 48}}, {"fold_id": 3, "model_name": "nn", "feature_name": "target_scores", "scores_valid": {"auroc": 0.8609920223346215, "cnt_samples": 1512, "cnt_features": 48}, "scores_test": {"auroc": 0.8720493501172293, "cnt_samples": 840, "cnt_features": 48}}, {"fold_id": 4, "model_name": "nn", "feature_name": "target_scores", "scores_valid": {"auroc": 0.8671989226967403, "cnt_samples": 1512, "cnt_features": 48}, "scores_test": {"auroc": 0.8700575903120802, "cnt_samples": 840, "cnt_features": 48}}]